{
  "@context": {
    "dc": "http://purl.org/dc/elements/1.1/",
    "foaf": "http://xmlns.com/foaf/0.1/",
    "v": "http://www.w3.org/2006/vcard/ns#",
    "dcterms": "http://purl.org/dc/terms/",
    "rdfs": "http://www.w3.org/2000/01/rdf-schema#",
    "cinii": "http://ci.nii.ac.jp/ns/1.0/"
  },
  "@id": "https://ci.nii.ac.jp/library/FA009767.json",
  "@graph": [
    {
      "@id": "https://ci.nii.ac.jp/library/FA009767#entity",
      "@type": [
        "foaf:Organization",
        "v:VCard"
      ],
      "foaf:isPrimaryTopicOf": {
        "@id": "https://ci.nii.ac.jp/library/FA009767.json"
      },
      "foaf:name": [
        {
          "@value": "農業・食品産業技術総合研究機構 果樹茶業研究部門 興津研究拠点"
        },
        {
          "@value": "ノウギョウ・ショクヒンサンギョウギジュツソウゴウケンキュウキコウ カジュチャギョウケンキュウブモン オキツケンキュウキョテン",
          "@language": "ja-hrkt"
        }
      ],
      "dcterms:alternative": [
        {
          "@value": "果樹茶興津"
        },
        {
          "@value": "カジュチャオキツ",
          "@language": "ja-hrkt"
        }
      ],
      "cinii:memberid": "FA009767",
      "cinii:organizationid": "KI005065",
      "cinii:prefcode": "22",
      "cinii:catflag": "A",
      "cinii:illflag": "A",
      "cinii:copyservice": "N",
      "cinii:loanservice": "N",
      "cinii:faxservice": "N",
      "cinii:illstatus": "N",
      "v:fn": "農業・食品産業技術総合研究機構 果樹茶業研究部門 興津研究拠点",
      "v:adr": {
        "@type": "v:Address",
        "v:postal-code": "424-0292",
        "v:label": "静岡県静岡市清水区興津中町485-6"
      }
    }
  ]
}
