{"@context":{"dc":"http://purl.org/dc/elements/1.1/","foaf":"http://xmlns.com/foaf/0.1/","v":"http://www.w3.org/2006/vcard/ns#","dcterms":"http://purl.org/dc/terms/","rdfs":"http://www.w3.org/2000/01/rdf-schema#","cinii":"http://ci.nii.ac.jp/ns/1.0/"},"@id":"http://ci.nii.ac.jp/library/FA017131.json","@graph":[{"@id":"http://ci.nii.ac.jp/library/FA017131#entity","@type":["foaf:Organization","v:VCard"],"foaf:isPrimaryTopicOf":{"@id":"http://ci.nii.ac.jp/library/FA017131.json"},"foaf:name":[{"@value":"群馬県立県民健康科学大学 図書館"},{"@value":"グンマケンリツケンミンケンコウカガクダイガク トシヨカン","@language":"ja-hrkt"}],"dcterms:alternative":[{"@value":"群健科大"},{"@value":"グンケンカダイ","@language":"ja-hrkt"}],"cinii:memberid":"FA017131","cinii:organizationid":"KI009725","cinii:prefcode":"10","cinii:catflag":"A","cinii:illflag":"A","cinii:copyservice":"A","cinii:loanservice":"A","cinii:faxservice":"N","cinii:illstatus":"A","v:fn":"群馬県立県民健康科学大学 図書館","v:adr":{"@type":"v:Address","v:postal-code":"371-0052","v:label":"群馬県前橋市上沖町323-1"},"v:tel":[{"@type":"v:Tel","@value":"027-235-9563"}],"v:fax":[{"@type":"v:Fax","@value":"027-235-2501"}],"dc:description":["Gunma Prefectural College of Health Sciences (NII)","323-1,Kamiokimachi,Maebashi-city,Gunma 371-0052","URL:http://gchs.opac.jp/(website)","来館利用担当:","電話番号:027-235-9563(直通)","受付時間(来館):開館時間内","注意事項:利用できるのは県内に在住・在勤・在学の18歳以上の方です。時期によって受付時間は変動するので、事前に問い合わせてください。","持参書類:身分証明書(貸出登録時)","複写時間:開館時間内","館外貸出:可","制限事項:一部図書及び雑誌は貸出不可","休館日:日曜日・国民の祝日,群馬県民の日(10月28日),年末年始,その他館長の定めた日","注記"]}]}