{
  "@context": {
    "dc": "http://purl.org/dc/elements/1.1/",
    "foaf": "http://xmlns.com/foaf/0.1/",
    "v": "http://www.w3.org/2006/vcard/ns#",
    "dcterms": "http://purl.org/dc/terms/",
    "rdfs": "http://www.w3.org/2000/01/rdf-schema#",
    "cinii": "http://ci.nii.ac.jp/ns/1.0/"
  },
  "@id": "http://ci.nii.ac.jp/library/FA009224.json",
  "@graph": [
    {
      "@id": "http://ci.nii.ac.jp/library/FA009224#entity",
      "@type": [
        "foaf:Organization",
        "v:VCard"
      ],
      "foaf:isPrimaryTopicOf": {
        "@id": "http://ci.nii.ac.jp/library/FA009224.json"
      },
      "foaf:name": [
        {
          "@value": "国立民族学博物館 情報管理施設"
        },
        {
          "@value": "コクリツミンゾクガクハクブツカン ジョウホウカンリシセツ",
          "@language": "ja-hrkt"
        }
      ],
      "dcterms:alternative": [
        {
          "@value": "民博"
        },
        {
          "@value": "ミンパク",
          "@language": "ja-hrkt"
        }
      ],
      "dcterms:hasPart": [
        "図"
      ],
      "cinii:memberid": "FA009224",
      "cinii:organizationid": "KI004663",
      "cinii:prefcode": "27",
      "cinii:mextid": "991200",
      "cinii:catflag": "A",
      "cinii:illflag": "A",
      "cinii:copyservice": "N",
      "cinii:loanservice": "N",
      "cinii:faxservice": "N",
      "cinii:illstatus": "N",
      "v:fn": "国立民族学博物館 情報管理施設",
      "v:adr": {
        "@type": "v:Address",
        "v:postal-code": "565-8511",
        "v:label": "大阪府吹田市千里万博公園10-1"
      },
      "v:tel": [
        {
          "@type": "v:Tel",
          "@value": "06-6878-8271(複依頼・貸借)"
        },
        {
          "@type": "v:Tel",
          "@value": "06-6878-8228(複写受付)"
        }
      ],
      "v:fax": [
        {
          "@type": "v:Fax",
          "@value": "06-6878-8249"
        }
      ],
      "dc:description": [
        "National Museum of Ethnology.  Library",
        "10-1 Senri Expo Park, Suita, Osaka, Japan 565-8511",
        "URL:http://www.minpaku.ac.jp/research/sharing/library (website)",
        "URL:http://www.minpaku.ac.jp/museum/information/access (map)",
        "来室利用担当:図書室カウンター",
        "電話番号:06-6878-8271",
        "休室日:日曜日、国の定める休日、水曜日および博物館休館日、年末年始(12/28-1/4)",
        "閲覧受付時間  : 10:00-17:00",
        "複写受付時間  : 10:00-16:00",
        "注意事項:利用希望の資料はあらかじめ所蔵調査をお願いします。",
        "注意事項:貴重図書・委員会指定資料・アーカイブズ資料の閲覧には事前申請が必要です。",
        "----------------- 以下、海外の図書館向けご案内です---------------------------------------------------------",
        "ILL-STAFF: Okuno / Terai / Hashimoto / Uenoyama / Inano",
        "ILL-Dept:Library Section",
        "ILL-Org:National Museum of Ethnology. Library",
        "ILL-Address:Senri Expo Park, Suita, Osaka, Japan",
        "ILL-Zip:565-8511",
        "ILL-Commun1:Tel:+81-6-6878-8228 / Fax:+81-6-6878-8249 / E-mail:nme-lib@minpaku.ac.jp",
        "ILL-Commun2:OPAC:http://lib.minpaku.ac.jp/",
        "ILL-Commun3:HOME-Page:http://www.minpaku.ac.jp/research/sharing/library",
        "ILL-Accept:Foreign(2):KERIS",
        "ILL-Sched:Closed:Wedonesdays,Sundays,National holidays,Dec.28-Jan.4",
        "ILL-Bill:Foreign(2):KERIS=NII Fee Management Service only",
        "ILL-Loan-Period:Loan:None",
        "ILL-Copy-Charge:PHOTOCOPY:35YEN per sheet / MCRFRM/PHOTOCOPY:40YEN per exposure / Postage required.Delivery method:via EMS only. No rush service available.",
        "ILL-Note:DIS:Photocopy:need the author's permission"
      ]
    }
  ]
}
