{
  "@context": {
    "dc": "http://purl.org/dc/elements/1.1/",
    "foaf": "http://xmlns.com/foaf/0.1/",
    "v": "http://www.w3.org/2006/vcard/ns#",
    "dcterms": "http://purl.org/dc/terms/",
    "rdfs": "http://www.w3.org/2000/01/rdf-schema#",
    "cinii": "http://ci.nii.ac.jp/ns/1.0/"
  },
  "@id": "http://ci.nii.ac.jp/library/FA005562.json",
  "@graph": [
    {
      "@id": "http://ci.nii.ac.jp/library/FA005562#entity",
      "@type": [
        "foaf:Organization",
        "v:VCard"
      ],
      "foaf:isPrimaryTopicOf": {
        "@id": "http://ci.nii.ac.jp/library/FA005562.json"
      },
      "foaf:name": [
        {
          "@value": "創価大学 中央図書館"
        },
        {
          "@value": "ソウカダイガク チュウオウトショカン",
          "@language": "ja-hrkt"
        }
      ],
      "dcterms:alternative": [
        {
          "@value": "創価大"
        },
        {
          "@value": "ソウカダイ",
          "@language": "ja-hrkt"
        }
      ],
      "dcterms:hasPart": [
        "創価女短",
        "中央",
        "工学部"
      ],
      "cinii:memberid": "FA005562",
      "cinii:organizationid": "KI002227",
      "cinii:prefcode": "13",
      "cinii:catflag": "A",
      "cinii:illflag": "A",
      "cinii:copyservice": "A",
      "cinii:loanservice": "A",
      "cinii:faxservice": "N",
      "cinii:illstatus": "N",
      "v:fn": "創価大学 中央図書館",
      "v:adr": {
        "@type": "v:Address",
        "v:postal-code": "192-8577",
        "v:label": "東京都八王子市丹木町1-236"
      },
      "v:tel": [
        {
          "@type": "v:Tel",
          "@value": "042-691-8218"
        }
      ],
      "v:fax": [
        {
          "@type": "v:Fax",
          "@value": "042-691-9336"
        }
      ],
      "dc:description": [
        "ILL-Staff:Masami Kuroha /Makoto Kimura",
        "ILL-Dept:ILL Section",
        "ILL-Org:Soka University Library",
        "ILL-Address:1-236 Tangi-machi,Hachiouji-shi, Tokyo, Japan",
        "ILL-Zip:192-8577",
        "ILL-Contact1:Tel:+81-0426918218 /Fax:+81-0426919336 / e-mail:sokaulib@soka.ac.jp",
        "ILL-Contact2:OPAC:http://sul.soka.ac.jp/",
        "ILL-Calender:Closed:Holiday, Dec 23-Jan 5",
        "ILL-Accept-method:International(1):OCLC(NII-OCLC ISO ILL Link only):UJX /",
        "ILL-Accept-method:International(2):KERIS(NII-KERIS ISO ILL Link only):UJX",
        "ILL-Payment-method:International:OCLC-IFM only",
        "ILL-Loan-Period:6 weeks per item /",
        "ILL-Loan-Item-Max:up to 5 items per library",
        "ILL-Loan-Renewal:None",
        "ILL-Loan-Charge:Foreign: 2000 YEN per volume; Postage required",
        "ILL-Loan-Delvery-method: via EMS only",
        "ILL-Non-Circulation:Special collection, mcrfrm, mcrfch, ref, per,news,a-v",
        "ILL-Copy-Charge:40 YEN per sheet",
        "ILL-Copy-Delivery-method:via EMS only",
        "ILL-OCLC-Symbol:UJX"
      ]
    }
  ]
}
