{
  "@context": {
    "dc": "http://purl.org/dc/elements/1.1/",
    "foaf": "http://xmlns.com/foaf/0.1/",
    "v": "http://www.w3.org/2006/vcard/ns#",
    "dcterms": "http://purl.org/dc/terms/",
    "rdfs": "http://www.w3.org/2000/01/rdf-schema#",
    "cinii": "http://ci.nii.ac.jp/ns/1.0/"
  },
  "@id": "http://ci.nii.ac.jp/library/FA018021.json",
  "@graph": [
    {
      "@id": "http://ci.nii.ac.jp/library/FA018021#entity",
      "@type": [
        "foaf:Organization",
        "v:VCard"
      ],
      "foaf:isPrimaryTopicOf": {
        "@id": "http://ci.nii.ac.jp/library/FA018021.json"
      },
      "foaf:name": [
        {
          "@value": "帝京平成大学 ちはら台キャンパス図書室"
        },
        {
          "@value": "テイキョウヘイセイダイガク チハラダイキャンパストショシツ",
          "@language": "ja-hrkt"
        }
      ],
      "dcterms:alternative": [
        {
          "@value": "帝京平成ちはら台"
        },
        {
          "@value": "テイキョウヘイセイチハラダイ",
          "@language": "ja-hrkt"
        }
      ],
      "cinii:memberid": "FA018021",
      "cinii:organizationid": "KI006895",
      "cinii:prefcode": "12",
      "cinii:catflag": "A",
      "cinii:illflag": "A",
      "cinii:copyservice": "A",
      "cinii:loanservice": "A",
      "cinii:faxservice": "N",
      "cinii:illstatus": "N",
      "v:fn": "帝京平成大学 ちはら台キャンパス図書室",
      "v:adr": {
        "@type": "v:Address",
        "v:postal-code": "290-0192",
        "v:label": "千葉県市原市ちはら台西6-19"
      },
      "v:tel": [
        {
          "@type": "v:Tel",
          "@value": "0436-74-9904"
        }
      ],
      "v:fax": [
        {
          "@type": "v:Fax",
          "@value": "0436-74-8921"
        }
      ],
      "dc:description": [
        "ILL-ZIP: 290-0192",
        "ILL-Org: Teikyo Heisei University Chiharadai Campus Library",
        ":ILL-Address: 6-19 Chiharadai-Nishi, Ichihara-shi, Chiba, JAPAN",
        "事前連絡:利用の前日までに電話にてご連絡ください。",
        "持参書類:紹介状、身分証明書",
        "休館日:日曜日、祝日、年末年始、蔵書点検、入学試験実施日、オープンキャンパス実施日など",
        "2013年4月1日より、帝京平成看護短期大学図書館は『帝京平成大学ちはら台キャンパス図書室』に名称変更いたしました。",
        "***担当者1名のため、即日処理や速達対応等に応じられない場合がございます。***"
      ]
    }
  ]
}
