{
  "@context": {
    "dc": "http://purl.org/dc/elements/1.1/",
    "foaf": "http://xmlns.com/foaf/0.1/",
    "v": "http://www.w3.org/2006/vcard/ns#",
    "dcterms": "http://purl.org/dc/terms/",
    "rdfs": "http://www.w3.org/2000/01/rdf-schema#",
    "cinii": "http://ci.nii.ac.jp/ns/1.0/"
  },
  "@id": "https://ci.nii.ac.jp/library/FA024374.json",
  "@graph": [
    {
      "@id": "https://ci.nii.ac.jp/library/FA024374#entity",
      "@type": [
        "foaf:Organization",
        "v:VCard"
      ],
      "foaf:isPrimaryTopicOf": {
        "@id": "https://ci.nii.ac.jp/library/FA024374.json"
      },
      "foaf:name": [
        {
          "@value": "独立行政法人 労働安全衛生総合研究所 (登戸地区図書館)"
        },
        {
          "@value": "ドクリツギョウセイホウジン ロウドウアンゼンエイセイソウゴウケンキュウジョ (ノボリトチクトショカン)",
          "@language": "ja-hrkt"
        }
      ],
      "dcterms:alternative": [
        {
          "@value": "安衛研"
        },
        {
          "@value": "アンエイケン",
          "@language": "ja-hrkt"
        }
      ],
      "dcterms:hasPart": [
        "登戸図"
      ],
      "cinii:memberid": "FA024374",
      "cinii:organizationid": "KI01477X",
      "cinii:prefcode": "14",
      "cinii:catflag": "A",
      "cinii:illflag": "A",
      "cinii:copyservice": "A",
      "cinii:loanservice": "N",
      "cinii:faxservice": "N",
      "cinii:illstatus": "A",
      "v:fn": "独立行政法人 労働安全衛生総合研究所 (登戸地区図書館)",
      "v:adr": {
        "@type": "v:Address",
        "v:postal-code": "214-8585",
        "v:label": "神奈川県川崎市多摩区長尾6-21-1"
      },
      "v:tel": [
        {
          "@type": "v:Tel",
          "@value": "044-865-6111"
        }
      ],
      "v:fax": [
        {
          "@type": "v:Fax",
          "@value": "044-865-6124"
        }
      ]
    }
  ]
}
