{
  "@context": {
    "dc": "http://purl.org/dc/elements/1.1/",
    "foaf": "http://xmlns.com/foaf/0.1/",
    "v": "http://www.w3.org/2006/vcard/ns#",
    "dcterms": "http://purl.org/dc/terms/",
    "rdfs": "http://www.w3.org/2000/01/rdf-schema#",
    "cinii": "http://ci.nii.ac.jp/ns/1.0/"
  },
  "@id": "https://ci.nii.ac.jp/library/FA003239.json",
  "@graph": [
    {
      "@id": "https://ci.nii.ac.jp/library/FA003239#entity",
      "@type": [
        "foaf:Organization",
        "v:VCard"
      ],
      "foaf:isPrimaryTopicOf": {
        "@id": "https://ci.nii.ac.jp/library/FA003239.json"
      },
      "foaf:name": [
        {
          "@value": "広島大学 図書館 霞図書館"
        },
        {
          "@value": "ヒロシマダイガク トショカン カスミトショカン",
          "@language": "ja-hrkt"
        }
      ],
      "dcterms:alternative": [
        {
          "@value": "広大霞"
        },
        {
          "@value": "ヒロダイカスミ",
          "@language": "ja-hrkt"
        }
      ],
      "dcterms:hasPart": [
        "医・解剖学",
        "医・神経生物学",
        "解剖共通",
        "医・心臓血管",
        "医・神経生理",
        "医・分子細胞",
        "医・医化学",
        "医・神経薬理",
        "医・分子病理",
        "医・病理学",
        "医・ウイルス学",
        "医・疫学・疾病",
        "公衛",
        "法医",
        "医・免疫学",
        "医・分子内科",
        "医・精神神経",
        "小児",
        "外科一",
        "脳外",
        "整形外科",
        "皮膚",
        "医・腎泌尿器",
        "医・視覚病態",
        "耳鼻咽喉科",
        "医・放射線診断",
        "産婦人科",
        "医・麻酔蘇生",
        "医・循環器内科",
        "薬・臨床薬物",
        "薬・生薬学",
        "薬・医薬分子",
        "薬・遺伝子制御",
        "薬・核酸分析化学",
        "薬・生体機能",
        "薬・創薬合成",
        "薬・生理化学",
        "薬・薬効解析",
        "薬・医療薬剤",
        "病・輸血部",
        "医病・病理診断",
        "医病・救急科",
        "病・薬剤部",
        "病・RI治療室",
        "病・検査部",
        "病・看護部",
        "歯・硬組織代謝",
        "歯・顎顔面解剖学",
        "歯・口腔生理",
        "歯・生体分子機能学",
        "歯・口腔顎顔面",
        "歯・細菌学",
        "歯・細胞分子薬理",
        "歯・生体材料",
        "歯・粘膜免疫",
        "歯・歯髄生物学",
        "歯・歯周病態学",
        "歯・分子口腔",
        "歯・口腔外科",
        "歯・先端歯科",
        "歯・歯科補綴",
        "歯・歯科矯正",
        "歯・小児歯科学",
        "歯・放射線",
        "原・放射線ゲノム",
        "原・ゲノム障害",
        "原・がん分子",
        "原・細胞修復",
        "原・放射線医療",
        "原・分子疫学",
        "原・計量生物",
        "原・疾患モデル",
        "原・血液腫瘍",
        "原・腫瘍外科",
        "原・被ばく資料",
        "医・脳神経内科",
        "薬学共通",
        "薬・細胞分子",
        "植物園",
        "資料館",
        "RI研",
        "病・手術部",
        "病・放射部",
        "病・材料部",
        "病・集中治療",
        "歯病・薬剤部",
        "歯病・看護部",
        "歯病・技士校",
        "歯病・衛士校",
        "医・保健",
        "図書館",
        "医・動物実験",
        "歯病・麻酔",
        "医病・総合内科",
        "原・放射線細胞",
        "原・分がん制御",
        "救急医学",
        "医病・リハビリ部",
        "病・医療情報",
        "医保・健康開発",
        "医保・健康情報",
        "医保・基礎看護",
        "医保・助産・母性",
        "医保・成人看護",
        "医保・小児看護",
        "医保・精神保健",
        "医保・成人健康",
        "老人看護A",
        "医保・地域在宅",
        "医保・地域学校",
        "医保・リハビリ",
        "医保・生体構造",
        "医保・生体運動",
        "医保・生体機能解析",
        "医保・生体環境",
        "医保・運動機能",
        "医保・生理機能",
        "医保・作業行動",
        "医保・感覚運動",
        "医保・精神機能",
        "医保・上肢機能",
        "原・放射線先端",
        "原・幹細胞機能",
        "原・放射線障害",
        "原・ゲノム発現",
        "原・放射線実験",
        "原・動物実験",
        "原・遺伝子実験",
        "歯病・特殊",
        "医保・老年がん",
        "血液・腫瘍",
        "薬・治療薬効",
        "原・線量測定",
        "歯・口腔保健工学",
        "歯・口腔保健衛生",
        "医病・研究推進セ",
        "図・書庫",
        "図・書庫2",
        "歯・公衆口腔保健",
        "歯・口腔保健疫学",
        "歯・口腔保健管理",
        "歯・生体構造",
        "歯・医療システム",
        "歯・口腔生物",
        "医・放射線腫瘍",
        "医病・がん化学療法",
        "薬・病態解析",
        "医病・内視鏡",
        "医病・リウマチ",
        "歯病・口腔総合",
        "歯・国際歯科",
        "歯病・歯科保存",
        "歯病・歯周",
        "歯病・顎・口腔外科",
        "歯病・口腔顎顔面",
        "歯病・口腔インプラント",
        "歯病・咬合・義歯",
        "歯病・口腔検査",
        "医・消化器・移植外科学",
        "医・消化器・代謝内科学",
        "医保・老年・地域作業",
        "医学教育センター",
        "医病・感染症"
      ],
      "cinii:memberid": "FA003239",
      "cinii:organizationid": "KI000720",
      "cinii:prefcode": "34",
      "cinii:mextid": "006202",
      "cinii:catflag": "A",
      "cinii:illflag": "A",
      "cinii:copyservice": "A",
      "cinii:loanservice": "A",
      "cinii:faxservice": "N",
      "cinii:illstatus": "A",
      "v:fn": "広島大学 図書館 霞図書館",
      "v:adr": {
        "@type": "v:Address",
        "v:postal-code": "734-8552",
        "v:label": "広島県広島市南区霞1-2-3"
      },
      "v:tel": [
        {
          "@type": "v:Tel",
          "@value": "082-257-5902"
        }
      ],
      "v:fax": [
        {
          "@type": "v:Fax",
          "@value": "082-257-5904"
        }
      ],
      "dc:description": [
        "来館利用担当:広島地区フロアサービス主担当",
        "電話番号:082-257-5902",
        "通常開館時間 :8:45〜21:00(土・日曜日10:00〜17:00)",
        "休館日 :日曜日・国民の祝日・年末年始・毎月第1,3月曜日午前中",
        "Hiroshima University Kasumi Library",
        "Kasumi 1-2-3, Minami-ku, Hiroshima 734-8552",
        "http://www.lib.hiroshima-u.ac.jp/",
        "ILL-Dept:Floor Service Section",
        "ILL-Org:Hiroshima Univ. Kasumi Library",
        "ILL-Adress:1-2-3 Kasumi, Minami-ku, Hiroshima, Japan",
        "ILL-Zip:734-8552",
        "ILL-Contact1:Tel:+81-82-257-5902 / Fax:+81-82-257-5904 / e-mail:tosho-fukyu-hiro@office.hiroshima-u.ac.jp",
        "ILL-Contact2: Online catalog:OPAC:http://opac.lib.hiroshima-u.ac.jp / Home-Page:http://www.lib.hiroshima-u.ac.jp",
        "POLICY:WEBPOLICY:ILL-Calender:Closed:Dec.27-Jan.4",
        "ILL-Accept:International: LOAN N/A",
        "ILL-Accept:International: COPY N/A",
        "ILL-Accept-method: Korea: KERIS=NII ILL Linkage (COPY only)",
        "ILL-Payment-method:  KERIS=NII Fee Management service Yes",
        "ILL-Loan-Period: N/A",
        "ILL-Loan-Item-Max: N/A",
        "ILL-Loan-Renewal: N/A",
        "ILL-Loan-Charge: N/A",
        "ILL-Loan-Delivery-method: N/A",
        "ILL-Non-Circulation-items: N/A",
        "ILL-Copy-Charge:Photocopy: 50 JPY per sheet / Postage is  required",
        "ILL-Copy-Delivery-method:Airmail"
      ]
    }
  ]
}
